LICENSE
MANIFEST.in
NOTICE
README.rst
pyproject.toml
setup.cfg
setup.py
airflow/providers/openstack/__init__.py
airflow/providers/openstack/get_provider_info.py
airflow/providers/openstack/hooks/__init__.py
airflow/providers/openstack/hooks/openstack.py
airflow/providers/openstack/sensors/__init__.py
airflow/providers/openstack/sensors/openstack.py
apache_airflow_providers_openstack.egg-info/PKG-INFO
apache_airflow_providers_openstack.egg-info/SOURCES.txt
apache_airflow_providers_openstack.egg-info/dependency_links.txt
apache_airflow_providers_openstack.egg-info/entry_points.txt
apache_airflow_providers_openstack.egg-info/not-zip-safe
apache_airflow_providers_openstack.egg-info/requires.txt
apache_airflow_providers_openstack.egg-info/top_level.txt