Metadata-Version: 2.1
Name: apache-airflow-providers-openstack
Version: 1.0.5
Summary: Provider package apache-airflow-providers-openstack for Apache Airflow
Author: Lukas Hameury
Author-email: lukas.hameury@libriciel.coop
License: Apache License 2.0
Classifier: Development Status :: 4 - Beta
Classifier: Environment :: Console
Classifier: Environment :: Web Environment
Classifier: Intended Audience :: Developers
Classifier: Intended Audience :: System Administrators
Classifier: License :: OSI Approved :: Apache Software License
Classifier: Programming Language :: Python :: 3.6
Classifier: Programming Language :: Python :: 3.7
Classifier: Programming Language :: Python :: 3.8
Classifier: Programming Language :: Python :: 3.9
Classifier: Topic :: System :: Monitoring
Requires-Python: ~=3.6
License-File: LICENSE
License-File: NOTICE
